{
  "name": "suitui",
  "version": "0.0.3",
  "description": "rem 自适应",
  "main": "src/index.js",
  "authors": "",
  "license": "ISC",
  "moduleType": [],
  "homepage": "",
  "ignore": [
    "**/.*",
    "node_modules",
    "bower_components",
    "test",
    "tests"
  ],
  "_release": "0.0.3",
  "_resolution": {
    "type": "version",
    "tag": "v0.0.3",
    "commit": "4187dba7b0db24cde4a19b84a45d8830101bc9d6"
  },
  "_source": "git@git.ucweb.local:pffe/component",
  "_target": "~0.0.3",
  "_originalSource": "git@git.ucweb.local:pffe/component",
  "_direct": true
}
